iobes/__init__.py
iobes/convert.py
iobes/parse.py
iobes/transition.py
iobes/utils.py
iobes/write.py
iobes-1.5.1.dist-info/LICENSE.txt
iobes-1.5.1.dist-info/METADATA
iobes-1.5.1.dist-info/WHEEL
iobes-1.5.1.dist-info/entry_points.txt
iobes-1.5.1.dist-info/top_level.txt
iobes-1.5.1.dist-info/RECORD
