Metadata-Version: 2.1
Name: iobes
Version: 1.5.1
Summary: Iobes
Home-page: https://github.com/blester125/iobes
Author: blester125
Author-email: blester125@gmail.com
License: MIT
Download-URL: https://github.com/blester125/iobes/archive/1.5.1.tar.gz
Platform: UNKNOWN
Classifier: License :: OSI Approved :: MIT License
Classifier: Intended Audience :: Science/Research
Classifier: Intended Audience :: Developers
Classifier: Development Status :: 3 - Alpha
Classifier: Topic :: Scientific/Engineering
Classifier: Programming Language :: Python :: 3 :: Only
Classifier: Environment :: Console
Classifier: Natural Language :: English
Requires-Python: >=3.6
Provides-Extra: mask
Requires-Dist: numpy ; extra == 'mask'
Provides-Extra: test
Requires-Dist: pytest ; extra == 'test'
